{
    "identityPoolName": "csrpnavigatore4d2e7f2_identitypool_e4d2e7f2",
    "allowUnauthenticatedIdentities": false,
    "resourceNameTruncated": "csrpnae4d2e7f2",
    "userPoolName": "csrpnavigatore4d2e7f2_userpool_e4d2e7f2",
    "autoVerifiedAttributes": [
        "email"
    ],
    "mfaConfiguration": "OPTIONAL",
    "mfaTypes": [
        "SMS Text Message"
    ],
    "smsAuthenticationMessage": "Your CSRP Navigator Authentication Code is: {####}",
    "smsVerificationMessage": "Your verification code is {####}",
    "emailVerificationSubject": "Your verification code",
    "emailVerificationMessage": "Your email verificatio code for CSRP Navigator is {####}",
    "defaultPasswordPolicy": false,
    "passwordPolicyMinLength": 8,
    "passwordPolicyCharacters": [],
    "requiredAttributes": [
        "email"
    ],
    "userpoolClientGenerateSecret": true,
    "userpoolClientRefreshTokenValidity": "365",
    "userpoolClientWriteAttributes": [
        "name",
        "phone_number",
        "preferred_username",
        "email"
    ],
    "userpoolClientReadAttributes": [
        "email"
    ],
    "userpoolClientLambdaRole": "csrpnae4d2e7f2_userpoolclient_lambda_role",
    "userpoolClientSetAttributes": true,
    "sharedId": "e4d2e7f2",
    "resourceName": "csrpnavigatore4d2e7f2",
    "authSelections": "identityPoolAndUserPool",
    "authRoleArn": {
        "Fn::GetAtt": [
            "AuthRole",
            "Arn"
        ]
    },
    "unauthRoleArn": {
        "Fn::GetAtt": [
            "UnauthRole",
            "Arn"
        ]
    },
    "useDefault": "manual",
    "usernameAttributes": [
        "email"
    ],
    "userPoolGroupList": [
        "CSRPNavigator"
    ],
    "serviceName": "Cognito",
    "dependsOn": [
        {
            "category": "function",
            "resourceName": "csrpnavigatore4d2e7f2CustomMessage",
            "triggerProvider": "Cognito",
            "attributes": [
                "Arn",
                "Name"
            ]
        }
    ],
    "thirdPartyAuth": false,
    "userPoolGroups": false,
    "adminQueries": true,
    "triggers": "{\n  \"CustomMessage\": [\n    \"verification-link\"\n  ]\n}",
    "hostedUI": false,
    "verificationBucketName": "csrpnavigatore4d2e7f2verificationbucket",
    "parentStack": {
        "Ref": "AWS::StackId"
    },
    "permissions": []
}